{
  "posts": [
    {
      "author": "f",
      "title": "g11",
      "body": "Lorem ipsum\n",
      "_collapsed": true,
      "id": 2
    },
    {
      "author": "d",
      "title": "d",
      "body": "d",
      "_collapsed": false,
      "id": 3
    },
    {
      "author": "va",
      "title": "ba",
      "body": "na",
      "_collapsed": true,
      "id": 4
    },
    {
      "author": "f",
      "title": "g",
      "body": "h",
      "id": 5
    },
    {
      "author": "gg",
      "title": "j",
      "body": "h",
      "_collapsed": false,
      "id": 6
    },
    {
      "author": "ff",
      "title": "s",
      "body": "a",
      "id": 7
    }
  ],
  "comments": [
    {
      "author": "adf",
      "email": "f",
      "body": "fa",
      "id": 2,
      "postId": 4
    },
    {
      "author": "aaa1",
      "email": "s1@a.com",
      "body": "f1",
      "id": 3,
      "postId": 3
    },
    {
      "author": "tt",
      "email": "yy",
      "body": "uu",
      "postId": 2,
      "id": 6
    },
    {
      "author": "ff",
      "email": "hh",
      "body": "gg",
      "postId": 2,
      "id": 7
    },
    {
      "author": "ddd",
      "email": "ddd@a.com",
      "body": "ddd",
      "id": 8,
      "postId": 6
    },
    {
      "author": "gg",
      "email": "ss",
      "body": "aa",
      "postId": 6,
      "id": 9
    },
    {
      "author": "a",
      "email": "d@a",
      "body": "g",
      "postId": 7,
      "id": 10
    },
    {
      "author": "f",
      "email": "a@d",
      "body": "g",
      "postId": 7,
      "id": 11
    },
    {
      "author": "f",
      "email": "a2@a.com",
      "body": "d",
      "postId": 4,
      "id": 12
    }
  ]
}